kobodl/__init__.py
kobodl/__main__.py
kobodl/actions.py
kobodl/app.py
kobodl/commands/__init__.py
kobodl/commands/book.py
kobodl/commands/user.py
kobodl/debug.py
kobodl/globals.py
kobodl/kobo.py
kobodl/koboDrmRemover.py
kobodl/settings.py
kobodl/templates/activation_form.html
kobodl/templates/books.j2
kobodl/templates/error.j2
kobodl/templates/footer.html
kobodl/templates/header.html
kobodl/templates/success.j2
kobodl/templates/users.j2
kobodl-0.12.0.dist-info/LICENSE.md
kobodl-0.12.0.dist-info/METADATA
kobodl-0.12.0.dist-info/WHEEL
kobodl-0.12.0.dist-info/entry_points.txt
kobodl-0.12.0.dist-info/RECORD
