Metadata-Version: 2.3
Name: kobodl
Version: 0.12.0
Summary: Kobo Book Downloader
License: Unlicense
Keywords: Kobo,eBook,Audiobook,Downloader,DRM
Author: Brandon Davis
Author-email: kobodl@subdavis.com
Requires-Python: >=3.9,<3.13
Classifier: License :: OSI Approved
Classifier: Programming Language :: Python :: 3
Classifier: Programming Language :: Python :: 3.9
Classifier: Programming Language :: Python :: 3.10
Classifier: Programming Language :: Python :: 3.11
Classifier: Programming Language :: Python :: 3.12
Requires-Dist: beautifulsoup4 (<5.0.0)
Requires-Dist: click (<9)
Requires-Dist: dataclasses (<1.0.0)
Requires-Dist: dataclasses-json (<0.6.0)
Requires-Dist: flask (==3.1.0)
Requires-Dist: pycryptodome (<4)
Requires-Dist: requests (>=2.25,<3.0)
Requires-Dist: setuptools (>=75.8.0,<76.0.0)
Requires-Dist: tabulate (<0.9.0)
Project-URL: Repository, https://github.com/subdavis/kobo-book-downloader.git
